{"name": "ENCHANTED_DARK_OAK_LOG", "history": [{"time": 1645239989077, "sellPrice": 401.9, "buyPrice": 474.2}, {"time": 1645241678884, "sellPrice": 398.5, "buyPrice": 474.9}, {"time": 1645243639063, "sellPrice": 397.2, "buyPrice": 474.0}, {"time": 1645245748909, "sellPrice": 396.7, "buyPrice": 472.1}, {"time": 1645247158942, "sellPrice": 396.5, "buyPrice": 471.5}, {"time": 1645248688905, "sellPrice": 399.6, "buyPrice": 471.0}, {"time": 1645250868913, "sellPrice": 399.9, "buyPrice": 470.8}, {"time": 1645252768894, "sellPrice": 400.1, "buyPrice": 473.3}, {"time": 1645254328988, "sellPrice": 400.1, "buyPrice": 473.1}, {"time": 1645255879007, "sellPrice": 400.2, "buyPrice": 472.8}, {"time": 1645258039047, "sellPrice": 399.7, "buyPrice": 465.2}, {"time": 1645259768950, "sellPrice": 396.2, "buyPrice": 464.5}, {"time": 1645261598970, "sellPrice": 396.0, "buyPrice": 464.5}, {"time": 1645263198896, "sellPrice": 396.0, "buyPrice": 473.5}, {"time": 1645265168906, "sellPrice": 396.5, "buyPrice": 472.6}, {"time": 1645266908904, "sellPrice": 399.8, "buyPrice": 465.7}, {"time": 1645268698898, "sellPrice": 400.1, "buyPrice": 465.6}, {"time": 1645270278893, "sellPrice": 400.0, "buyPrice": 465.4}, {"time": 1645272548940, "sellPrice": 400.1, "buyPrice": 463.1}, {"time": 1645274888903, "sellPrice": 410.8, "buyPrice": 458.2}, {"time": 1645276109085, "sellPrice": 411.2, "buyPrice": 457.4}, {"time": 1645277508896, "sellPrice": 410.9, "buyPrice": 457.8}, {"time": 1645279538945, "sellPrice": 400.7, "buyPrice": 456.1}, {"time": 1645281088951, "sellPrice": 406.6, "buyPrice": 456.1}, {"time": 1645283248999, "sellPrice": 406.8, "buyPrice": 455.3}, {"time": 1645284938899, "sellPrice": 406.8, "buyPrice": 456.3}, {"time": 1645286868988, "sellPrice": 406.8, "buyPrice": 455.6}, {"time": 1645289318892, "sellPrice": 407.3, "buyPrice": 456.1}, {"time": 1645290348963, "sellPrice": 407.3, "buyPrice": 454.1}, {"time": 1645291908914, "sellPrice": 408.1, "buyPrice": 454.9}, {"time": 1645294008946, "sellPrice": 408.3, "buyPrice": 456.7}, {"time": 1645295848914, "sellPrice": 406.8, "buyPrice": 456.9}, {"time": 1645297448945, "sellPrice": 407.1, "buyPrice": 457.0}, {"time": 1645299098904, "sellPrice": 407.3, "buyPrice": 454.8}, {"time": 1645301239030, "sellPrice": 406.2, "buyPrice": 452.6}, {"time": 1645302788961, "sellPrice": 406.5, "buyPrice": 446.6}, {"time": 1645304718930, "sellPrice": 407.2, "buyPrice": 444.9}, {"time": 1645306298947, "sellPrice": 406.2, "buyPrice": 445.3}, {"time": 1645308378950, "sellPrice": 369.2, "buyPrice": 444.0}, {"time": 1645310048888, "sellPrice": 370.3, "buyPrice": 439.5}, {"time": 1645311938917, "sellPrice": 370.5, "buyPrice": 442.0}, {"time": 1645313588947, "sellPrice": 370.5, "buyPrice": 441.5}, {"time": 1645317019112, "sellPrice": 372.0, "buyPrice": 442.4}, {"time": 1645322209115, "sellPrice": 372.7, "buyPrice": 430.0}, {"time": 1645323968938, "sellPrice": 372.2, "buyPrice": 430.0}, {"time": 1645325159008, "sellPrice": 372.6, "buyPrice": 429.9}, {"time": 1645326389085, "sellPrice": 372.7, "buyPrice": 430.0}, {"time": 1645328098913, "sellPrice": 372.6, "buyPrice": 429.1}, {"time": 1645330038893, "sellPrice": 372.9, "buyPrice": 438.0}, {"time": 1645332148926, "sellPrice": 372.9, "buyPrice": 442.9}, {"time": 1645333658980, "sellPrice": 372.8, "buyPrice": 442.2}, {"time": 1645335078909, "sellPrice": 369.1, "buyPrice": 441.4}, {"time": 1645337238917, "sellPrice": 369.2, "buyPrice": 440.8}, {"time": 1645339156140, "sellPrice": 369.3, "buyPrice": 441.2}, {"time": 1645340766160, "sellPrice": 369.2, "buyPrice": 440.4}, {"time": 1645342286135, "sellPrice": 369.2, "buyPrice": 440.8}, {"time": 1645344506156, "sellPrice": 369.3, "buyPrice": 440.2}, {"time": 1645346166123, "sellPrice": 369.6, "buyPrice": 441.3}, {"time": 1645348006140, "sellPrice": 369.7, "buyPrice": 441.3}, {"time": 1645349566156, "sellPrice": 369.7, "buyPrice": 434.0}, {"time": 1645351576184, "sellPrice": 369.8, "buyPrice": 433.7}, {"time": 1645353286144, "sellPrice": 373.1, "buyPrice": 433.9}, {"time": 1645355106160, "sellPrice": 369.7, "buyPrice": 433.4}, {"time": 1645356686128, "sellPrice": 369.8, "buyPrice": 432.2}, {"time": 1645358946155, "sellPrice": 370.3, "buyPrice": 432.0}, {"time": 1645361306166, "sellPrice": 370.5, "buyPrice": 430.2}, {"time": 1645362506206, "sellPrice": 370.5, "buyPrice": 427.2}, {"time": 1645363876258, "sellPrice": 373.2, "buyPrice": 426.4}, {"time": 1645365936315, "sellPrice": 370.5, "buyPrice": 428.3}, {"time": 1645367486132, "sellPrice": 370.5, "buyPrice": 429.6}, {"time": 1645369586188, "sellPrice": 370.5, "buyPrice": 411.0}, {"time": 1645371356188, "sellPrice": 370.6, "buyPrice": 411.1}, {"time": 1645373236189, "sellPrice": 371.6, "buyPrice": 426.8}, {"time": 1645375686179, "sellPrice": 372.0, "buyPrice": 428.8}, {"time": 1645376736137, "sellPrice": 371.6, "buyPrice": 429.3}, {"time": 1645378316138, "sellPrice": 370.8, "buyPrice": 427.8}, {"time": 1645380426130, "sellPrice": 370.7, "buyPrice": 425.0}, {"time": 1645382256135, "sellPrice": 370.8, "buyPrice": 421.6}, {"time": 1645383916166, "sellPrice": 371.2, "buyPrice": 419.6}, {"time": 1645385496138, "sellPrice": 373.6, "buyPrice": 415.9}, {"time": 1645387606155, "sellPrice": 371.2, "buyPrice": 419.6}, {"time": 1645389186149, "sellPrice": 371.2, "buyPrice": 423.2}, {"time": 1645391166158, "sellPrice": 370.8, "buyPrice": 417.2}, {"time": 1645392686119, "sellPrice": 370.9, "buyPrice": 417.0}, {"time": 1645394766141, "sellPrice": 371.3, "buyPrice": 417.0}, {"time": 1645396416140, "sellPrice": 371.2, "buyPrice": 415.8}, {"time": 1645398316146, "sellPrice": 371.5, "buyPrice": 414.1}, {"time": 1645399966150, "sellPrice": 371.3, "buyPrice": 414.0}, {"time": 1645403196131, "sellPrice": 370.6, "buyPrice": 415.8}, {"time": 1645407466170, "sellPrice": 370.3, "buyPrice": 415.2}, {"time": 1645410066158, "sellPrice": 370.4, "buyPrice": 410.9}, {"time": 1645411386163, "sellPrice": 370.5, "buyPrice": 410.8}, {"time": 1645412826154, "sellPrice": 371.0, "buyPrice": 410.9}, {"time": 1645414546140, "sellPrice": 370.3, "buyPrice": 409.9}, {"time": 1645416506159, "sellPrice": 370.3, "buyPrice": 409.7}, {"time": 1645418616133, "sellPrice": 370.3, "buyPrice": 409.4}, {"time": 1645419966498, "sellPrice": 369.6, "buyPrice": 409.5}, {"time": 1645421486150, "sellPrice": 369.7, "buyPrice": 410.0}, {"time": 1645423726156, "sellPrice": 369.6, "buyPrice": 409.9}, {"time": 1645425666147, "sellPrice": 369.9, "buyPrice": 409.8}, {"time": 1645427216153, "sellPrice": 370.0, "buyPrice": 417.0}, {"time": 1645428686151, "sellPrice": 369.9, "buyPrice": 415.9}, {"time": 1645430896152, "sellPrice": 370.3, "buyPrice": 415.8}, {"time": 1645432656130, "sellPrice": 370.1, "buyPrice": 416.0}, {"time": 1645434446148, "sellPrice": 370.2, "buyPrice": 416.0}, {"time": 1645436056149, "sellPrice": 370.2, "buyPrice": 415.6}, {"time": 1645438266148, "sellPrice": 370.2, "buyPrice": 415.0}, {"time": 1645439806150, "sellPrice": 370.2, "buyPrice": 414.8}, {"time": 1645441516135, "sellPrice": 370.8, "buyPrice": 413.7}, {"time": 1645443086148, "sellPrice": 371.8, "buyPrice": 413.4}, {"time": 1645445436271, "sellPrice": 372.3, "buyPrice": 412.2}, {"time": 1645447866160, "sellPrice": 372.4, "buyPrice": 413.7}, {"time": 1645449086144, "sellPrice": 372.4, "buyPrice": 413.7}, {"time": 1645450426135, "sellPrice": 372.4, "buyPrice": 412.9}, {"time": 1645452686234, "sellPrice": 373.0, "buyPrice": 413.8}, {"time": 1645454076172, "sellPrice": 372.5, "buyPrice": 413.9}, {"time": 1645456336206, "sellPrice": 373.0, "buyPrice": 409.8}, {"time": 1645457876136, "sellPrice": 373.1, "buyPrice": 409.0}, {"time": 1645459736141, "sellPrice": 373.1, "buyPrice": 408.8}, {"time": 1645462176141, "sellPrice": 373.0, "buyPrice": 408.6}, {"time": 1645463236182, "sellPrice": 372.9, "buyPrice": 408.9}, {"time": 1645464796206, "sellPrice": 373.3, "buyPrice": 414.4}, {"time": 1645466836154, "sellPrice": 372.5, "buyPrice": 413.7}, {"time": 1645468706145, "sellPrice": 372.5, "buyPrice": 409.9}, {"time": 1645470256150, "sellPrice": 372.5, "buyPrice": 409.8}, {"time": 1645471896133, "sellPrice": 372.5, "buyPrice": 399.7}, {"time": 1645473996150, "sellPrice": 370.0, "buyPrice": 410.0}, {"time": 1645475616169, "sellPrice": 369.8, "buyPrice": 408.9}, {"time": 1645477456293, "sellPrice": 370.3, "buyPrice": 407.8}, {"time": 1645479106150, "sellPrice": 370.2, "buyPrice": 405.9}, {"time": 1645481176144, "sellPrice": 370.1, "buyPrice": 408.8}, {"time": 1645482836154, "sellPrice": 369.9, "buyPrice": 408.9}, {"time": 1645484786147, "sellPrice": 369.8, "buyPrice": 408.4}, {"time": 1645486396148, "sellPrice": 369.8, "buyPrice": 408.3}, {"time": 1645489556174, "sellPrice": 370.0, "buyPrice": 408.2}, {"time": 1645493876161, "sellPrice": 369.9, "buyPrice": 408.1}, {"time": 1645496476152, "sellPrice": 370.0, "buyPrice": 408.0}, {"time": 1645497856153, "sellPrice": 369.9, "buyPrice": 408.3}, {"time": 1645499216141, "sellPrice": 370.0, "buyPrice": 408.4}, {"time": 1645500936146, "sellPrice": 370.1, "buyPrice": 408.8}, {"time": 1645502856145, "sellPrice": 370.0, "buyPrice": 408.7}, {"time": 1645504976133, "sellPrice": 369.8, "buyPrice": 408.9}, {"time": 1645506376151, "sellPrice": 369.9, "buyPrice": 408.9}, {"time": 1645507886149, "sellPrice": 369.8, "buyPrice": 410.0}, {"time": 1645510076157, "sellPrice": 369.8, "buyPrice": 409.6}, {"time": 1645512016164, "sellPrice": 369.3, "buyPrice": 410.0}, {"time": 1645513536149, "sellPrice": 369.3, "buyPrice": 409.9}, {"time": 1645515086144, "sellPrice": 369.4, "buyPrice": 409.7}, {"time": 1645517286162, "sellPrice": 369.3, "buyPrice": 409.9}, {"time": 1645519056144, "sellPrice": 369.3, "buyPrice": 409.6}, {"time": 1645520846147, "sellPrice": 369.3, "buyPrice": 409.3}, {"time": 1645522416307, "sellPrice": 369.4, "buyPrice": 408.8}, {"time": 1645524476159, "sellPrice": 369.4, "buyPrice": 409.3}, {"time": 1645526186166, "sellPrice": 369.4, "buyPrice": 409.8}, {"time": 1645527996143, "sellPrice": 371.5, "buyPrice": 409.8}, {"time": 1645529496162, "sellPrice": 371.5, "buyPrice": 409.5}, {"time": 1645531896158, "sellPrice": 369.6, "buyPrice": 409.9}, {"time": 1645534336221, "sellPrice": 369.4, "buyPrice": 409.7}, {"time": 1645535526164, "sellPrice": 369.8, "buyPrice": 409.9}, {"time": 1645536846206, "sellPrice": 369.5, "buyPrice": 409.5}, {"time": 1645538776152, "sellPrice": 369.7, "buyPrice": 409.9}, {"time": 1645540306153, "sellPrice": 369.3, "buyPrice": 409.7}, {"time": 1645542676152, "sellPrice": 369.4, "buyPrice": 409.3}, {"time": 1645544536182, "sellPrice": 369.6, "buyPrice": 409.1}, {"time": 1645546396216, "sellPrice": 369.4, "buyPrice": 409.0}, {"time": 1645548626172, "sellPrice": 369.6, "buyPrice": 405.8}, {"time": 1645549926152, "sellPrice": 369.5, "buyPrice": 409.8}, {"time": 1645551246159, "sellPrice": 369.6, "buyPrice": 410.0}, {"time": 1645553276142, "sellPrice": 369.5, "buyPrice": 409.9}, {"time": 1645555156201, "sellPrice": 370.0, "buyPrice": 410.0}, {"time": 1645556666146, "sellPrice": 371.2, "buyPrice": 409.7}, {"time": 1645558296162, "sellPrice": 369.6, "buyPrice": 409.6}, {"time": 1645560406224, "sellPrice": 370.3, "buyPrice": 409.6}, {"time": 1645562016137, "sellPrice": 369.5, "buyPrice": 413.9}, {"time": 1645563886160, "sellPrice": 369.5, "buyPrice": 414.0}, {"time": 1645565516133, "sellPrice": 369.4, "buyPrice": 413.7}, {"time": 1645567556147, "sellPrice": 369.4, "buyPrice": 413.5}, {"time": 1645569256167, "sellPrice": 369.6, "buyPrice": 413.2}, {"time": 1645571186150, "sellPrice": 370.0, "buyPrice": 413.1}, {"time": 1645572846153, "sellPrice": 370.1, "buyPrice": 412.6}, {"time": 1645576226138, "sellPrice": 370.3, "buyPrice": 410.6}, {"time": 1645581596143, "sellPrice": 370.7, "buyPrice": 409.2}, {"time": 1645583596451, "sellPrice": 371.2, "buyPrice": 409.5}, {"time": 1645585596158, "sellPrice": 370.7, "buyPrice": 404.5}, {"time": 1645587306186, "sellPrice": 370.4, "buyPrice": 404.1}, {"time": 1645589246122, "sellPrice": 370.1, "buyPrice": 401.2}, {"time": 1645591356158, "sellPrice": 370.1, "buyPrice": 400.5}, {"time": 1645592766164, "sellPrice": 370.2, "buyPrice": 401.6}, {"time": 1645594286151, "sellPrice": 370.1, "buyPrice": 401.7}, {"time": 1645596486145, "sellPrice": 370.1, "buyPrice": 401.9}, {"time": 1645598436147, "sellPrice": 370.2, "buyPrice": 401.8}, {"time": 1645599986123, "sellPrice": 370.1, "buyPrice": 402.1}, {"time": 1645601486138, "sellPrice": 370.2, "buyPrice": 402.3}, {"time": 1645603666226, "sellPrice": 369.8, "buyPrice": 397.0}, {"time": 1645605406161, "sellPrice": 369.7, "buyPrice": 403.8}, {"time": 1645607176134, "sellPrice": 369.6, "buyPrice": 410.1}, {"time": 1645608686257, "sellPrice": 369.5, "buyPrice": 410.3}, {"time": 1645610856144, "sellPrice": 369.5, "buyPrice": 405.9}, {"time": 1645612576148, "sellPrice": 369.6, "buyPrice": 406.0}, {"time": 1645614296142, "sellPrice": 369.4, "buyPrice": 406.0}, {"time": 1645615886142, "sellPrice": 369.4, "buyPrice": 406.0}, {"time": 1645618236148, "sellPrice": 369.5, "buyPrice": 402.2}, {"time": 1645620696136, "sellPrice": 369.6, "buyPrice": 402.2}, {"time": 1645621906143, "sellPrice": 369.7, "buyPrice": 401.7}, {"time": 1645623266124, "sellPrice": 369.3, "buyPrice": 402.3}, {"time": 1645625096145, "sellPrice": 369.7, "buyPrice": 401.3}, {"time": 1645626976210, "sellPrice": 371.6, "buyPrice": 400.0}, {"time": 1645629076159, "sellPrice": 371.2, "buyPrice": 399.0}, {"time": 1645630936218, "sellPrice": 369.7, "buyPrice": 397.0}, {"time": 1645632736137, "sellPrice": 370.3, "buyPrice": 396.7}, {"time": 1645635136160, "sellPrice": 369.8, "buyPrice": 396.7}, {"time": 1645636266153, "sellPrice": 370.1, "buyPrice": 397.0}, {"time": 1645637786130, "sellPrice": 369.9, "buyPrice": 399.3}, {"time": 1645639646142, "sellPrice": 369.8, "buyPrice": 396.7}, {"time": 1645641496154, "sellPrice": 369.4, "buyPrice": 397.9}, {"time": 1645643076142, "sellPrice": 372.5, "buyPrice": 400.0}, {"time": 1645644706172, "sellPrice": 372.6, "buyPrice": 400.1}, {"time": 1645646826172, "sellPrice": 372.7, "buyPrice": 402.0}, {"time": 1645648436169, "sellPrice": 372.5, "buyPrice": 401.9}, {"time": 1645650366124, "sellPrice": 372.5, "buyPrice": 401.9}, {"time": 1645651986160, "sellPrice": 369.2, "buyPrice": 401.4}, {"time": 1645653976131, "sellPrice": 351.0, "buyPrice": 384.8}, {"time": 1645655696137, "sellPrice": 351.0, "buyPrice": 382.7}, {"time": 1645657606188, "sellPrice": 351.0, "buyPrice": 381.9}, {"time": 1645659266137, "sellPrice": 350.1, "buyPrice": 381.5}, {"time": 1645662446131, "sellPrice": 350.1, "buyPrice": 381.3}, {"time": 1645667244123, "sellPrice": 350.1, "buyPrice": 381.4}, {"time": 1645669774148, "sellPrice": 350.2, "buyPrice": 382.7}, {"time": 1645671084107, "sellPrice": 350.0, "buyPrice": 383.0}, {"time": 1645671964107, "sellPrice": 350.0, "buyPrice": 383.3}, {"time": 1645673654114, "sellPrice": 350.2, "buyPrice": 383.3}, {"time": 1645675654114, "sellPrice": 350.0, "buyPrice": 383.2}, {"time": 1645677774123, "sellPrice": 350.0, "buyPrice": 401.7}, {"time": 1645679174122, "sellPrice": 350.2, "buyPrice": 401.9}, {"time": 1645680684111, "sellPrice": 350.0, "buyPrice": 401.8}, {"time": 1645682894093, "sellPrice": 350.2, "buyPrice": 401.9}, {"time": 1645684844125, "sellPrice": 350.2, "buyPrice": 405.4}, {"time": 1645686384113, "sellPrice": 350.2, "buyPrice": 405.4}, {"time": 1645687904110, "sellPrice": 350.3, "buyPrice": 405.3}, {"time": 1645690084108, "sellPrice": 350.0, "buyPrice": 405.1}, {"time": 1645691834110, "sellPrice": 350.0, "buyPrice": 405.1}, {"time": 1645693614111, "sellPrice": 350.3, "buyPrice": 405.3}, {"time": 1645695244118, "sellPrice": 350.0, "buyPrice": 405.2}, {"time": 1645697194111, "sellPrice": 350.2, "buyPrice": 405.4}, {"time": 1645698994112, "sellPrice": 350.2, "buyPrice": 399.9}, {"time": 1645700754120, "sellPrice": 350.5, "buyPrice": 399.9}, {"time": 1645702294115, "sellPrice": 395.3, "buyPrice": 400.0}, {"time": 1645704644116, "sellPrice": 395.8, "buyPrice": 404.9}, {"time": 1645707124119, "sellPrice": 351.0, "buyPrice": 405.2}, {"time": 1645708334122, "sellPrice": 351.0, "buyPrice": 404.7}, {"time": 1645709674117, "sellPrice": 351.0, "buyPrice": 405.0}, {"time": 1645711644119, "sellPrice": 353.9, "buyPrice": 404.9}, {"time": 1645713154107, "sellPrice": 353.9, "buyPrice": 404.5}, {"time": 1645715474107, "sellPrice": 350.1, "buyPrice": 404.1}, {"time": 1645717044104, "sellPrice": 352.8, "buyPrice": 404.7}, {"time": 1645719094113, "sellPrice": 350.2, "buyPrice": 398.9}, {"time": 1645721384133, "sellPrice": 352.8, "buyPrice": 398.8}, {"time": 1645722464097, "sellPrice": 352.8, "buyPrice": 398.9}, {"time": 1645724044131, "sellPrice": 353.1, "buyPrice": 404.3}, {"time": 1645726084191, "sellPrice": 353.3, "buyPrice": 405.1}, {"time": 1645727974109, "sellPrice": 353.1, "buyPrice": 405.3}, {"time": 1645729454115, "sellPrice": 352.9, "buyPrice": 405.4}, {"time": 1645731324118, "sellPrice": 355.4, "buyPrice": 401.0}, {"time": 1645733254107, "sellPrice": 350.0, "buyPrice": 400.1}, {"time": 1645734824182, "sellPrice": 350.1, "buyPrice": 399.5}, {"time": 1645736804144, "sellPrice": 350.0, "buyPrice": 396.7}, {"time": 1645738364120, "sellPrice": 350.0, "buyPrice": 396.9}, {"time": 1645740414103, "sellPrice": 350.5, "buyPrice": 396.9}, {"time": 1645742094131, "sellPrice": 350.0, "buyPrice": 396.8}, {"time": 1645744024098, "sellPrice": 350.1, "buyPrice": 395.7}, {"time": 1645745654117, "sellPrice": 350.0, "buyPrice": 395.6}, {"time": 1645748864130, "sellPrice": 350.2, "buyPrice": 395.9}, {"time": 1645753534120, "sellPrice": 167.9, "buyPrice": 405.0}, {"time": 1645756014110, "sellPrice": 186.8, "buyPrice": 380.3}, {"time": 1645757304106, "sellPrice": 220.4, "buyPrice": 405.0}, {"time": 1645758394128, "sellPrice": 221.5, "buyPrice": 403.9}, {"time": 1645760124112, "sellPrice": 225.0, "buyPrice": 402.7}, {"time": 1645762074101, "sellPrice": 226.1, "buyPrice": 368.0}, {"time": 1645764164106, "sellPrice": 233.5, "buyPrice": 366.2}, {"time": 1645765574256, "sellPrice": 226.8, "buyPrice": 365.5}, {"time": 1645767084114, "sellPrice": 228.3, "buyPrice": 364.3}, {"time": 1645769294117, "sellPrice": 230.6, "buyPrice": 361.1}, {"time": 1645771255716, "sellPrice": 231.1, "buyPrice": 359.6}, {"time": 1645772785727, "sellPrice": 231.7, "buyPrice": 359.8}, {"time": 1645774285728, "sellPrice": 232.3, "buyPrice": 346.8}, {"time": 1645776485728, "sellPrice": 232.4, "buyPrice": 346.8}, {"time": 1645778235699, "sellPrice": 234.5, "buyPrice": 345.1}, {"time": 1645780015717, "sellPrice": 238.0, "buyPrice": 344.9}, {"time": 1645781635712, "sellPrice": 285.6, "buyPrice": 344.0}, {"time": 1645783605730, "sellPrice": 286.5, "buyPrice": 342.1}, {"time": 1645785405727, "sellPrice": 289.2, "buyPrice": 342.5}, {"time": 1645787095708, "sellPrice": 292.0, "buyPrice": 343.4}, {"time": 1645788685708, "sellPrice": 292.2, "buyPrice": 343.5}, {"time": 1645791025713, "sellPrice": 291.9, "buyPrice": 342.7}, {"time": 1645793445731, "sellPrice": 291.1, "buyPrice": 357.8}, {"time": 1645794685754, "sellPrice": 290.7, "buyPrice": 366.2}, {"time": 1645796035761, "sellPrice": 290.8, "buyPrice": 399.9}, {"time": 1645797965715, "sellPrice": 291.7, "buyPrice": 399.9}, {"time": 1645799515764, "sellPrice": 291.8, "buyPrice": 400.0}, {"time": 1645801645755, "sellPrice": 292.0, "buyPrice": 398.5}, {"time": 1645803455748, "sellPrice": 291.9, "buyPrice": 399.3}, {"time": 1645805345721, "sellPrice": 307.1, "buyPrice": 399.1}, {"time": 1645807785823, "sellPrice": 298.9, "buyPrice": 398.2}, {"time": 1645808865802, "sellPrice": 298.3, "buyPrice": 397.7}, {"time": 1645810445752, "sellPrice": 300.4, "buyPrice": 396.3}, {"time": 1645812435736, "sellPrice": 302.3, "buyPrice": 398.3}, {"time": 1645814375721, "sellPrice": 304.4, "buyPrice": 402.8}, {"time": 1645815945713, "sellPrice": 306.1, "buyPrice": 399.6}, {"time": 1645817495776, "sellPrice": 311.7, "buyPrice": 399.8}, {"time": 1645819595767, "sellPrice": 312.7, "buyPrice": 399.3}, {"time": 1645821225750, "sellPrice": 307.7, "buyPrice": 399.5}, {"time": 1645823055733, "sellPrice": 310.0, "buyPrice": 399.3}, {"time": 1645824705723, "sellPrice": 311.2, "buyPrice": 398.6}, {"time": 1645826795740, "sellPrice": 312.0, "buyPrice": 390.2}, {"time": 1645828495719, "sellPrice": 313.2, "buyPrice": 399.6}, {"time": 1645830405753, "sellPrice": 305.7, "buyPrice": 402.4}, {"time": 1645832035717, "sellPrice": 306.3, "buyPrice": 401.8}, {"time": 1645835155780, "sellPrice": 307.1, "buyPrice": 401.1}, {"time": 1645839345707, "sellPrice": 308.7, "buyPrice": 399.7}, {"time": 1645842275722, "sellPrice": 307.5, "buyPrice": 400.4}, {"time": 1645843615801, "sellPrice": 312.7, "buyPrice": 399.3}, {"time": 1645844805719, "sellPrice": 312.8, "buyPrice": 399.5}, {"time": 1645846505708, "sellPrice": 313.5, "buyPrice": 398.6}, {"time": 1645848455724, "sellPrice": 313.3, "buyPrice": 398.6}, {"time": 1645850555906, "sellPrice": 313.5, "buyPrice": 398.4}, {"time": 1645851965726, "sellPrice": 314.3, "buyPrice": 398.5}, {"time": 1645853475719, "sellPrice": 313.5, "buyPrice": 398.3}, {"time": 1645856026117, "sellPrice": 322.1, "buyPrice": 399.5}, {"time": 1645857605718, "sellPrice": 313.7, "buyPrice": 399.7}, {"time": 1645859155741, "sellPrice": 313.4, "buyPrice": 399.8}, {"time": 1645860685774, "sellPrice": 313.4, "buyPrice": 399.6}, {"time": 1645862845732, "sellPrice": 313.3, "buyPrice": 400.0}, {"time": 1645864595723, "sellPrice": 313.7, "buyPrice": 400.2}, {"time": 1645866335729, "sellPrice": 313.6, "buyPrice": 400.7}, {"time": 1645867945923, "sellPrice": 313.8, "buyPrice": 400.3}, {"time": 1645870035721, "sellPrice": 313.9, "buyPrice": 400.2}, {"time": 1645871725752, "sellPrice": 314.3, "buyPrice": 400.2}]}